{"type":"View","props":{"width":750,"visible":true,"height":1334,"autoDestroyAtClosed":false},"compId":2,"child":[{"type":"Sprite","props":{"y":-168,"x":750,"visible":true,"texture":"game/timg.jpg","rotation":90,"height":750},"compId":3},{"type":"Sprite","props":{"zOrder":1,"y":-42,"x":401,"width":330,"texture":"game/npc.png","rotation":90,"height":418},"compId":8},{"type":"Script","props":{"runtime":"GameStart/GameStart.js"},"compId":15},{"type":"Sprite","props":{"y":1125,"x":86,"texture":"game/exit.png","rotation":90},"compId":34},{"type":"Sprite","props":{"y":379,"x":599,"texture":"game/dialog-bg.png","rotation":90},"compId":35},{"type":"Text","props":{"y":506,"x":561,"wordWrap":true,"width":324,"valign":"middle","text":"文案文案文案文案文案文案文案文案文案文案文案文案文案文案文案文案文案文案","rotation":90,"leading":10,"height":152,"fontSize":25,"font":"Microsoft YaHei","color":"#ffffff","align":"center","runtime":"laya.display.Text"},"compId":36},{"type":"Sprite","props":{"y":860,"x":544.5,"width":33,"texture":"game/close.png","height":32},"compId":37},{"type":"Sprite","props":{"y":696,"x":401,"width":76,"texture":"game/no.png","rotation":90,"height":47},"compId":38},{"type":"Sprite","props":{"y":582,"x":401,"width":76,"visible":true,"texture":"game/yes.png","rotation":90,"height":47},"compId":39},{"type":"Sprite","props":{"y":175,"x":296,"width":933,"texture":"game/bg_g.png","rotation":90,"height":246},"compId":41},{"type":"Text","props":{"y":262,"x":249,"wordWrap":true,"width":700,"text":"对话对话对话对话对话对话对话对话对话对话对话对话对话对话","rotation":90,"leading":8,"height":149,"fontSize":28,"font":"Microsoft YaHei","color":"#ffffff","runtime":"laya.display.Text"},"compId":42},{"type":"Sprite","props":{"y":971,"x":61.00000000000001},"compId":49,"child":[{"type":"Label","props":{"x":24.999999999999993,"valign":"middle","text":">>> 继续","rotation":90,"fontSize":25,"font":"Microsoft YaHei","color":"#bfbfbf","bold":false,"align":"center"},"compId":48}]}],"loadList":["game/timg.jpg","game/npc.png","game/exit.png","game/dialog-bg.png","game/close.png","game/no.png","game/yes.png","game/bg_g.png"],"loadList3D":[]}